{
  "projection_registry": {
    "MASTER_VIEW": {
      "route": "/",
      "panels": [
        "identity",
        "simulation",
        "time",
        "state",
        "memory",
        "entities",
        "relationships",
        "signals",
        "events",
        "anomalies",
        "metrics",
        "telemetry",
        "topology",
        "network",
        "continuity",
        "lineage",
        "reasoning",
        "goals",
        "tasks",
        "agents",
        "vectors",
        "clusters",
        "regions",
        "layers",
        "views",
        "scene",
        "animation",
        "render",
        "output",
        "debug"
      ]
    },
    "EXECUTIVE_VIEW": {
      "route": "/executive",
      "panels": [
        "mission_control",
        "goals",
        "tasks",
        "agents",
        "reasoning",
        "metrics",
        "alerts",
        "timeline"
      ]
    },
    "SYSTEM_VIEW": {
      "route": "/system",
      "panels": [
        "identity",
        "simulation",
        "state",
        "metrics",
        "telemetry",
        "continuity",
        "lineage"
      ]
    },
    "MEMORY_VIEW": {
      "route": "/memory",
      "panels": [
        "stable_memory",
        "working_memory",
        "episodic_memory",
        "semantic_memory",
        "latent_memory"
      ]
    },
    "GRAPH_VIEW": {
      "route": "/graph",
      "panels": [
        "entities",
        "relationships",
        "signals",
        "events",
        "topology"
      ]
    },
    "VECTOR_VIEW": {
      "route": "/vector",
      "panels": [
        "vectors",
        "clusters",
        "regions",
        "latent_space"
      ]
    },
    "NETWORK_VIEW": {
      "route": "/network",
      "panels": [
        "network",
        "signals",
        "telemetry",
        "topology"
      ]
    },
    "REASONING_VIEW": {
      "route": "/reasoning",
      "panels": [
        "active_problem",
        "objectives",
        "attention",
        "hypotheses",
        "predictions"
      ]
    },
    "RENDER_VIEW": {
      "route": "/render",
      "panels": [
        "scene",
        "camera",
        "layers",
        "animation",
        "projections"
      ]
    },
    "TELEMETRY_VIEW": {
      "route": "/telemetry",
      "panels": [
        "metrics",
        "telemetry",
        "events",
        "anomalies"
      ]
    },
    "DEBUG_VIEW": {
      "route": "/debug",
      "panels": [
        "logs",
        "trace",
        "events",
        "statistics"
      ]
    }
  },
  "ui": {
    "active_view": "MASTER_VIEW",
    "navigation": [],
    "panels": {
      "identity": {
        "title": "Identity",
        "widgets": [],
        "actions": []
      },
      "simulation": {
        "title": "Simulation",
        "widgets": [],
        "actions": []
      },
      "time": {
        "title": "Time",
        "widgets": [],
        "actions": []
      },
      "state": {
        "title": "State",
        "widgets": [],
        "actions": []
      },
      "memory": {
        "title": "Memory",
        "widgets": [],
        "actions": []
      },
      "entities": {
        "title": "Entities",
        "widgets": [],
        "actions": []
      },
      "relationships": {
        "title": "Relationships",
        "widgets": [],
        "actions": []
      },
      "signals": {
        "title": "Signals",
        "widgets": [],
        "actions": []
      },
      "events": {
        "title": "Events",
        "widgets": [],
        "actions": []
      },
      "anomalies": {
        "title": "Anomalies",
        "widgets": [],
        "actions": []
      },
      "metrics": {
        "title": "Metrics",
        "widgets": [],
        "actions": []
      },
      "telemetry": {
        "title": "Telemetry",
        "widgets": [],
        "actions": []
      },
      "topology": {
        "title": "Topology",
        "widgets": [],
        "actions": []
      },
      "network": {
        "title": "Network",
        "widgets": [],
        "actions": []
      },
      "continuity": {
        "title": "Continuity",
        "widgets": [],
        "actions": []
      },
      "lineage": {
        "title": "Lineage",
        "widgets": [],
        "actions": []
      },
      "reasoning": {
        "title": "Reasoning",
        "widgets": [],
        "actions": []
      },
      "goals": {
        "title": "Goals",
        "widgets": [],
        "actions": []
      },
      "tasks": {
        "title": "Tasks",
        "widgets": [],
        "actions": []
      },
      "agents": {
        "title": "Agents",
        "widgets": [],
        "actions": []
      },
      "vectors": {
        "title": "Vectors",
        "widgets": [],
        "actions": []
      },
      "clusters": {
        "title": "Clusters",
        "widgets": [],
        "actions": []
      },
      "regions": {
        "title": "Regions",
        "widgets": [],
        "actions": []
      },
      "layers": {
        "title": "Layers",
        "widgets": [],
        "actions": []
      },
      "views": {
        "title": "Views",
        "widgets": [],
        "actions": []
      },
      "scene": {
        "title": "Scene",
        "widgets": [],
        "actions": []
      },
      "animation": {
        "title": "Animation",
        "widgets": [],
        "actions": []
      },
      "render": {
        "title": "Render",
        "widgets": [],
        "actions": []
      },
      "output": {
        "title": "Output",
        "widgets": [],
        "actions": []
      },
      "debug": {
        "title": "Debug",
        "widgets": [],
        "actions": []
      }
    }
  }
}